Metadata-Version: 2.1
Name: talking-assist
Version: 0.0.1
Summary: Virtual assistant
Home-page: https://github.com/shubhamjainjnsb/talking_assist
Author: shubham jain
Author-email: jains5833@gmail.com
License: UNKNOWN
Platform: UNKNOWN
Classifier: Programming Language :: Python :: 3
Classifier: License :: OSI Approved :: MIT License
Classifier: Operating System :: OS Independent
Requires-Python: >=3.5
